{
  "forge_marker":1,
  "defaults": {
    "textures": {
      "particle": "forgecraft:items/iron/0",
      "texture": "forgecraft:items/iron/0"
    },
    "parent": "forgecraft:block/saw_block_model"
  },
  "variants": {
    "active=false,facing=north": { "model": "forgecraft:saw_block_model" },
    "active=false,facing=east":  { "model": "forgecraft:saw_block_model", "y": 90 },
    "active=false,facing=south": { "model": "forgecraft:saw_block_model", "y": 180 },
    "active=false,facing=west":  { "model": "forgecraft:saw_block_model", "y": 270 },
    "active=true,facing=north": { "model": "forgecraft:saw_block_model" },
    "active=true,facing=east":  { "model": "forgecraft:saw_block_model", "y": 90 },
    "active=true,facing=south": { "model": "forgecraft:saw_block_model", "y": 180 },
    "active=true,facing=west":  { "model": "forgecraft:saw_block_model", "y": 270 }
  }
}